{
    "type": "object",
    "properties": {
        "usuario": {
            "$ref": "Usuarios.json"
        },
        "nivelSocioeconomico": {
            "type": "object",
            "properties": {
                "ingresosMes": {
                    "type": "string"
                },
                "educacion": {
                    "type": "string"
                },
                "ocupacion": {
                    "type": "string"
                },
                "diasDeTrabajoXsemana": {
                    "type": "number"
                },
                "modalidad": {
                    "type": "string"
                },
                "horarioEntrada": {
                    "type": "string"
                },
                "horarioSalida": {
                    "type": "string"
                },
                "dineroDeAlimentacionXmesIndivi": {
                    "type": "string"
                },
                "dineroDeAlimentacionXmesHogar": {
                    "type": "string"
                }
            },
            "required": [
                "ingresosMes",
                "educacion",
                "ocupacion",
                "diasDeTrabajoXsemana",
                "modalidad",
                "horarioEntrada",
                "horarioSalida",
                "dineroDeAlimentacionXmesIndivi",
                "dineroDeAlimentacionXmesHogar"
            ]
        }
    },
    "required": [
        "usuario"
    ]
}