{
    "type": "object",
    "properties": {
        "usuario": {
            "$ref": "Usuarios.json"
        },
        "maternaExclusiva": {
            "type": "string"
        },
        "artificial": {
            "type": "string"
        },
        "mixta": {
            "type": "string"
        },
        "maternaContemplada": {
            "type": "string"
        },
        "mixtaContemplada": {
            "type": "string"
        },
        "artificialContemplada": {
            "type": "string"
        }
    },
    "required": [
        "usuario",
        "maternaExclusiva",
        "artificial",
        "mixta",
        "maternaContemplada",
        "mixtaContemplada",
        "artificialContemplada"
    ]
}